foundry/__init__.py
foundry/main.py
foundry/core/Data.py
foundry/core/UndoController.py
foundry/core/__init__.py
foundry/core/file.py
foundry/core/geometry.py
foundry/core/gui.py
foundry/core/icon.py
foundry/core/menu.py
foundry/core/namespace.py
foundry/core/palette.py
foundry/core/redux_store.py
foundry/core/tasks.py
foundry/core/validators.py
foundry/core/blocks/Block.py
foundry/core/blocks/BlockGroup.py
foundry/core/blocks/__init__.py
foundry/core/blocks/util.py
foundry/core/drawable/Drawable.py
foundry/core/drawable/__init__.py
foundry/core/graphics_page/GraphicsGroup.py
foundry/core/graphics_page/GraphicsPage.py
foundry/core/graphics_page/__init__.py
foundry/core/graphics_set/GraphicsSet.py
foundry/core/graphics_set/__init__.py
foundry/core/graphics_set/util.py
foundry/core/painter/Painter.py
foundry/core/painter/__init__.py
foundry/core/player_animations/PlayerAnimation.py
foundry/core/player_animations/PlayerAnimationData.py
foundry/core/player_animations/__init__.py
foundry/core/player_animations/util.py
foundry/core/sprites/Sprite.py
foundry/core/sprites/SpriteGroup.py
foundry/core/sprites/__init__.py
foundry/core/tiles/__init__.py
foundry/core/tiles/util.py
foundry/core/warnings/EnemyCompatibilityWarning.py
foundry/core/warnings/ExtendToGroundWarning.py
foundry/core/warnings/InvalidObjectWarning.py
foundry/core/warnings/InvalidPositionWarning.py
foundry/core/warnings/InvalidSizeWarning.py
foundry/core/warnings/InvalidWarpWarning.py
foundry/core/warnings/OutsideLevelBoundsWarning.py
foundry/core/warnings/Warning.py
foundry/core/warnings/WarningCreator.py
foundry/core/warnings/WarningType.py
foundry/core/warnings/__init__.py
foundry/core/warnings/util.py
foundry/data/Default.pal
foundry/data/__init__.py
foundry/data/definitions.json
foundry/data/enemy_definitions.json
foundry/data/foundry.ico
foundry/data/gfx.png
foundry/data/gui_styles.json
foundry/data/jump_creator_flags.json
foundry/data/levels.json
foundry/data/main_window_flags.json
foundry_smb3-0.6.1.post1.dist-info/METADATA
foundry_smb3-0.6.1.post1.dist-info/WHEEL
foundry_smb3-0.6.1.post1.dist-info/entry_points.txt
foundry_smb3-0.6.1.post1.dist-info/top_level.txt
foundry_smb3-0.6.1.post1.dist-info/RECORD
