Metadata-Version: 2.1
Name: foundry-smb3
Version: 0.6.1.post1
Summary: The future of SMB3
Home-page: https://github.com/TheJoeSmo/Foundry
Author: TheJoeSmo
Author-email: joesmo.joesmo12@gmail.com
License: GPL3
Classifier: License :: OSI Approved :: GNU General Public License v3 (GPLv3)
Classifier: Intended Audience :: Other Audience
Classifier: Natural Language :: English
Classifier: Programming Language :: Python :: 3
Classifier: Programming Language :: Python :: 3 :: Only
Classifier: Operating System :: OS Independent
Classifier: Operating System :: Microsoft :: Windows
Classifier: Operating System :: POSIX :: Linux
Classifier: Operating System :: iOS
Classifier: Topic :: Games/Entertainment
Requires-Python: >=3.10
Requires-Dist: PySide6 (>=6.3.1)
Requires-Dist: attrs (>=22.1.0)
Requires-Dist: pydantic (>=1.9.2)
Requires-Dist: qt-material (>=2.12)
Requires-Dist: single-source (>=0.3.0)
Requires-Dist: dill (>=0.3.5)
Requires-Dist: six (>=1.16.0)
Requires-Dist: nest-asyncio (>=1.5.6)
Requires-Dist: numpy (>=1.23.4)
Requires-Dist: func-timeout (>=4.3.0)
